widget_dropdown/__init__.py
widget_dropdown/static/widget.css
widget_dropdown/static/widget.js
widget_dropdown-0.4.1.dist-info/METADATA
widget_dropdown-0.4.1.dist-info/WHEEL
widget_dropdown-0.4.1.dist-info/RECORD
