Metadata-Version: 2.4
Name: widget-dropdown
Version: 0.4.1
Requires-Dist: anywidget
Provides-Extra: dev
Requires-Dist: jupyterlab; extra == 'dev'
Requires-Dist: watchfiles; extra == 'dev'
